Workbook

Sheet INC
A1: EXCEL MODELING TEST
A2: Income Statement
A3: (INR, Millions)
B4: 2021 | C4: 2022 | D4: 2023 | E4: 2024 | F4: 2025 | G4: 2026 | H4: 2027 | I4: 2028 | J4: 2029
A6: Net Sales | B6: 75.8 | C6: 94.3 | D6: 108.3 | E6: 125.1 | F6: =INC!F29 -> 150.3402 | G6: =INC!G29 -> 182.17628 | H6: =INC!H29 -> 222.57573 | I6: =INC!I29 -> 274.15993 | J6: =INC!J29 -> 340.4409
A8: Cost of Goods Sold | B8: 49.4 | C8: 59.8 | D8: 69.5 | E8: 81.8 | F8: =INC!F31 -> 96.653588 | G8: =INC!G31 -> 115.07423 | H8: =INC!H31 -> 138.67921 | I8: =INC!I31 -> 168.40901 | J8: =INC!J31 -> 206.07001
A10: SG&A | B10: 22.6 | C10: 29.3 | D10: 32.5 | E10: 37.3 | F10: =INC!F35 -> 39.79162 | G10: =INC!G35 -> 44.047125 | H10: =INC!H35 -> 49.216064 | I10: =INC!I35 -> 55.549579 | J10: =INC!J35 -> 63.380963
A11: Fixed SG &A | B11: 14 | C11: 20 | D11: 22 | E11: 25
A12: Variable SG&A | B12: 8.6 | C12: 9.3 | D12: 10.5 | E12: 12.3
A14: Provision for warranty | E14: 0.2 | F14: =INC!F44 -> 1.503402 | G14: =INC!G44 -> 1.8217628 | H14: =INC!H44 -> 2.2257573 | I14: =INC!I44 -> 2.7415993 | J14: =INC!J44 -> 3.404409
A16: Depreciation | B16: 1.7 | C16: 2.2 | D16: 2.8 | E16: 3.5 | F16: =INC!F42 -> 2.745 | G16: =INC!G42 -> 2.70825 | H16: =INC!H42 -> 2.6020125 | I16: =INC!I42 -> 2.0617106 | J16: =INC!J42 -> 2.352454
A18: Net Interest Expense | B18: 0.3 | C18: 0.5 | D18: 0.3 | E18: 0.8 | F18: =INC!F48 -> 1.224 | G18: =INC!G48 -> 1.824 | H18: =INC!H48 -> 1.644 | I18: =INC!I48 -> 1.164 | J18: =INC!J48 -> 0.984
A20: Income Taxes | B20: 0.6 | C20: 0.9 | D20: 1.2 | E20: 0.7 | F20: =INC!F51 -> 2.5267784 | G20: =INC!G51 -> 5.0102719 | H20: =INC!H51 -> 8.4626077 | I20: =INC!I51 -> 13.270212 | J20: =INC!J51 -> 19.274719
A22: Dividends | B22: - | C22: - | D22: - | E22: - | F22: =INC!F54 -> 0.29479081 | G22: =INC!G54 -> 0.58453173 | H22: =INC!H54 -> 0.98730423 | I22: =INC!I54 -> 1.5481914 | J22: =INC!J54 -> 2.2487172
A25: Construct the Income Statement of the company showing Gross Profit, EBITDA, EBIT & Net Profit
B28: 2021 | C28: 2022 | D28: 2023 | E28: 2024 | F28: 2025 | G28: 2026 | H28: 2027 | I28: 2028 | J28: 2029
A29: Net Sales | B29: 75.8 | C29: 94.3 | D29: 108.3 | E29: 125.1 | F29: =E29*(1+F30) -> 150.3402 | G29: =F29*(1+G30) -> 182.17628 | H29: =G29*(1+H30) -> 222.57573 | I29: =H29*(1+I30) -> 274.15993 | J29: =I29*(1+J30) -> 340.4409
A30: Sales Growth (%) | E30: 0.182 | F30: =(((E29/B29)^(1/3))-1)+2% -> 0.20176022 | G30: =F30+1% -> 0.21176022 | H30: =G30+1% -> 0.22176022 | I30: =H30+1% -> 0.23176022 | J30: =I30+1% -> 0.24176022
A31: COGS | B31: 49.4 | C31: 59.8 | D31: 69.5 | E31: 81.8 | F31: =E31*(1+F32) -> 96.653588 | G31: =F31*(1+G32) -> 115.07423 | H31: =G31*(1+H32) -> 138.67921 | I31: =H31*(1+I32) -> 168.40901 | J31: =I31*(1+J32) -> 206.07001
A32: COGS Growth (%) | E32: =E31/D31-1 -> 0.17697842 | F32: =F30*90% -> 0.1815842 | G32: =G30*90% -> 0.1905842 | H32: =H30*92.5% -> 0.20512821 | I32: =I30*92.5% -> 0.21437821 | J32: =J30*92.5% -> 0.22362821
A33: Gross Profit | B33: 26.4 | C33: 34.4 | D33: 38.7 | E33: 43.3 | F33: =F29-F31 -> 53.686616 | G33: =G29-G31 -> 67.102045 | H33: =H29-H31 -> 83.896526 | I33: =I29-I31 -> 105.75093 | J33: =J29-J31 -> 134.37089
A35: SG&A | B35: 22.6 | C35: 29.3 | D35: 32.5 | E35: 37.3 | F35: =F36+F38 -> 39.79162 | G35: =G36+G38 -> 44.047125 | H35: =H36+H38 -> 49.216064 | I35: =I36+I38 -> 55.549579 | J35: =J36+J38 -> 63.380963
A36: Fixed SG &A | B36: 14 | C36: 20 | D36: 22 | E36: 25 | F36: =E36*(1+F37) -> 26.261001 | G36: =F36*(1+G37) -> 27.65126 | H36: =G36*(1+H37) -> 29.184248 | I36: =H36*(1+I37) -> 30.875185 | J36: =I36*(1+J37) -> 32.741283
A37: Fixed SG&A Growth (%) | F37: =F30*25% -> 0.050440056 | G37: =G30*25% -> 0.052940056 | H37: =H30*25% -> 0.055440056 | I37: =I30*25% -> 0.057940056 | J37: =J30*25% -> 0.060440056
A38: Variable SG&A | B38: 8.6 | C38: 9.3 | D38: 10.5 | E38: 12.3 | F38: =F29*F39 -> 13.530618 | G38: =G29*G39 -> 16.395865 | H38: =H29*H39 -> 20.031816 | I38: =I29*I39 -> 24.674394 | J38: =J29*J39 -> 30.639681
A39: Variable( as % of sales) | E39: =9% -> 0.09 | F39: =9% -> 0.09 | G39: =9% -> 0.09 | H39: =9% -> 0.09 | I39: =9% -> 0.09 | J39: =9% -> 0.09
A40: EBITDA | B40: 3.8 | C40: 5.1 | D40: 6.2 | E40: 6 | F40: =F33-F35 -> 13.894997 | G40: =G33-G35 -> 23.054919 | H40: =H33-H35 -> 34.680462 | I40: =I33-I35 -> 50.201349 | J40: =J33-J35 -> 70.989927
A42: Depreciation | B42: 1.7 | C42: 2.2 | D42: 2.8 | E42: 3.5 | F42: =BS!E12*15% -> 2.745 | G42: =BS!F12*15% -> 2.70825 | H42: =BS!G12*15% -> 2.6020125 | I42: =BS!H12*15% -> 2.0617106 | J42: =BS!I12*15% -> 2.352454
A43: Depreciation (%) | F43: =15% -> 0.15
A44: Provision for Warranty | B44: 0 | C44: 0 | D44: 0 | E44: 0.2 | F44: =F29*F45 -> 1.503402 | G44: =G29*G45 -> 1.8217628 | H44: =H29*H45 -> 2.2257573 | I44: =I29*I45 -> 2.7415993 | J44: =J29*J45 -> 3.404409
A45: Provision (%) | F45: =1% -> 0.01 | G45: =1% -> 0.01 | H45: =1% -> 0.01 | I45: =1% -> 0.01 | J45: =1% -> 0.01
A46: EBIT | B46: 2.09 | C46: 2.95 | D46: 3.41 | E46: 2.29 | F46: =F40-F42-F44 -> 9.6465945 | G46: =G40-G42-G44 -> 18.524906 | H46: =H40-H42-H44 -> 29.852692 | I46: =I40-I42-I44 -> 45.398039 | J46: =J40-J42-J44 -> 65.233064
A48: Interest | B48: 0.3 | C48: 0.5 | D48: 0.3 | E48: 0.8 | F48: =(BS!E22+BS!E23)*6% -> 1.224 | G48: =(BS!F22+BS!F23)*IF(F46/F48<6,7%,6%) -> 1.824 | H48: =(BS!G22+BS!G23)*IF(G46/G48<6,7%,6%) -> 1.644 | I48: =(BS!H22+BS!H23)*IF(H46/H48<6,7%,6%) -> 1.164 | J48: =(BS!I22+BS!I23)*IF(I46/I48<6,7%,6%) -> 0.984
A49: PBT | B49: 1.8 | C49: 2.5 | D49: 3.1 | E49: 1.5 | F49: =F46-F48 -> 8.4225945 | G49: =G46-G48 -> 16.700906 | H49: =H46-H48 -> 28.208692 | I49: =I46-I48 -> 44.234039 | J49: =J46-J48 -> 64.249064
A51: Tax | B51: 0.6 | C51: 0.9 | D51: 1.2 | E51: 0.7 | F51: =F49*30% -> 2.5267784 | G51: =G49*30% -> 5.0102719 | H51: =H49*30% -> 8.4626077 | I51: =I49*30% -> 13.270212 | J51: =J49*30% -> 19.274719
A53: Net Profit | B53: 1.2 | C53: 1.6 | D53: 1.9 | E53: 0.8 | F53: =F49-F51 -> 5.8958162 | G53: =G49-G51 -> 11.690635 | H53: =H49-H51 -> 19.746085 | I53: =I49-I51 -> 30.963827 | J53: =J49-J51 -> 44.974345
A54: Dividend Payout | F54: =F53*5% -> 0.29479081 | G54: =G53*5% -> 0.58453173 | H54: =H53*5% -> 0.98730423 | I54: =I53*5% -> 1.5481914 | J54: =J53*5% -> 2.2487172

Sheet BS
A1: EXCEL MODELING TEST
A2: Balance Sheet
A3: (INR, Millions)
D4: 2023 | E4: 2024 | F4: 2025 | G4: 2026 | H4: 2027 | I4: 2028 | J4: 2029
A6: Cash and Equivalents | D6: 0.4 | E6: 1 | F6: =CFS!E42 -> 6.1667634 | G6: =CFS!F42 -> 7.7432126 | H6: =CFS!G42 -> 19.833196 | I6: =CFS!H42 -> 30.372705 | J6: =CFS!I42 -> 51.493465
A7: Accounts Receivables | D7: 5.5 | E7: 5.8 | F7: =INC!F29*(E7/INC!E29) -> 6.9702093 | G7: =INC!G29*(F7/INC!F29) -> 8.4462224 | H7: =INC!H29*(G7/INC!G29) -> 10.319259 | I7: =INC!I29*(H7/INC!H29) -> 12.710852 | J7: =INC!J29*(I7/INC!I29) -> 15.783831
A8: Inventory | D8: 28.5 | E8: 31.4 | F8: =INC!F29*(E8/INC!E29) -> 37.735271 | G8: =INC!G29*(F8/INC!F29) -> 45.7261 | H8: =INC!H29*(G8/INC!G29) -> 55.866331 | I8: =INC!I29*(H8/INC!H29) -> 68.813924 | J8: =INC!J29*(I8/INC!I29) -> 85.450394
A9: Other Current Assets | D9: 4.5 | E9: 5.7 | F9: =INC!F29*(E9/INC!E29) -> 6.8500333 | G9: =INC!G29*(F9/INC!F29) -> 8.3005978 | H9: =INC!H29*(G9/INC!G29) -> 10.14134 | I9: =INC!I29*(H9/INC!H29) -> 12.4917 | J9: =INC!J29*(I9/INC!I29) -> 15.511696
A10: Current Assets | D10: 38.9 | E10: =SUM(E6:E9) -> 43.9 | F10: =SUM(F6:F9) -> 57.722277 | G10: =SUM(G6:G9) -> 70.216133 | H10: =SUM(H6:H9) -> 96.160126 | I10: =SUM(I6:I9) -> 124.38918 | J10: =SUM(J6:J9) -> 168.23939
A12: Net Property, Plant and Equipment (Net Block) | D12: 17.1 | E12: 18.3 | F12: =E12-CFS!E20-INC!F42 -> 18.055 | G12: =F12-CFS!F20-INC!G42 -> 17.34675 | H12: =G12-CFS!G20-INC!H42 -> 13.744737 | I12: =H12-CFS!H20-INC!I42 -> 15.683027 | J12: =I12-CFS!I20-INC!J42 -> 18.830573
A13: Other Long-term Assets (Land) | D13: 3.6 | E13: 2.5 | F13: =E13 -> 2.5 | G13: =F13 -> 2.5 | H13: =G13 -> 2.5 | I13: =H13 -> 2.5 | J13: =I13 -> 2.5
A14: Investment In Subsidiary | D14: - | E14: - | F14: =5 -> 5 | G14: =F14 -> 5 | H14: =G14*(1-40%) -> 3 | I14: =H14 -> 3 | J14: =0 -> 0
A15: Total Assets | D15: 59.6 | E15: =SUM(E10,E12:E14) -> 64.7 | F15: =SUM(F10,F12:F14) -> 83.277277 | G15: =SUM(G10,G12:G14) -> 95.062883 | H15: =SUM(H10,H12:H14) -> 115.40486 | I15: =SUM(I10,I12:I14) -> 145.57221 | J15: =SUM(J10,J12:J14) -> 189.56996
A18: Accounts Payable | D18: 6.7 | E18: 4.8 | F18: =INC!F29*(E18/INC!E29) -> 5.7684491 | G18: =INC!G29*(F18/INC!F29) -> 6.9899771 | H18: =INC!H29*(G18/INC!G29) -> 8.540076 | I18: =INC!I29*(H18/INC!H29) -> 10.519326 | J18: =INC!J29*(I18/INC!I29) -> 13.062481
A19: Other Current Liabilities | D19: 4.1 | E19: 2.5 | F19: =INC!F29*(E19/INC!E29) -> 3.0044006 | G19: =INC!G29*(F19/INC!F29) -> 3.6406131 | H19: =INC!H29*(G19/INC!G29) -> 4.4479563 | I19: =INC!I29*(H19/INC!H29) -> 5.4788156 | J19: =INC!J29*(I19/INC!I29) -> 6.8033753
A20: Current Liabilities | D20: 10.8 | E20: 7.3 | F20: =SUM(F18:F19) -> 8.7728496 | G20: =SUM(G18:G19) -> 10.63059 | H20: =SUM(H18:H19) -> 12.988032 | I20: =SUM(I18:I19) -> 15.998142 | J20: =SUM(J18:J19) -> 19.865856
A22: Debt | D22: 7.6 | E22: 15.4 | F22: =E22+10 -> 25.4 | G22: =F22-3 -> 22.4 | H22: =G22-3 -> 19.4 | I22: =H22-3 -> 16.4 | J22: =I22-3 -> 13.4
A23: Convertible Bond -2027 | D23: 5 | E23: 5 | F23: =E23 -> 5 | G23: =F23 -> 5 | H23: =0 -> 0 | I23: =H23 -> 0 | J23: =I23 -> 0
A24: Other Long-Term Liabilities | D24: 0.2 | E24: 0.1 | F24: =E24 -> 0.1 | G24: =F24 -> 0.1 | H24: =G24 -> 0.1 | I24: =H24 -> 0.1 | J24: =I24 -> 0.1
A25: Provision for warranty | E25: 0.2 | F25: =E25+INC!F44 -> 1.703402 | G25: =F25+INC!G44 -> 3.5251648 | H25: =G25+INC!H44 -> 5.7509221 | I25: =H25+INC!I44-2 -> 6.4925215 | J25: =I25+INC!J44-3 -> 6.8969305
A26: Total Liabilities | D26: 23.6 | E26: 28 | F26: =SUM(F20,F22:F25) -> 40.976252 | G26: =SUM(G20,G22:G25) -> 41.655755 | H26: =SUM(H20,H22:H25) -> 38.238954 | I26: =SUM(I20,I22:I25) -> 38.990663 | J26: =SUM(J20,J22:J25) -> 40.262786
A28: Shareholders' Equity | D28: 36 | E28: 36.8 | F28: =E28+INC!F53-INC!F54+(E23-F23) -> 42.401025 | G28: =F28+INC!G53-INC!G54+(F23-G23) -> 53.507128 | H28: =G28+INC!H53-INC!H54+(G23-H23) -> 77.265909 | I28: =H28+INC!I53-INC!I54+(H23-I23) -> 106.68154 | J28: =I28+INC!J53-INC!J54+(I23-J23) -> 149.40717
A30: Total Liabilities and SHE | D30: 59.6 | E30: 64.8 | F30: =F26+F28 -> 83.377277 | G30: =G26+G28 -> 95.162883 | H30: =H26+H28 -> 115.50486 | I30: =I26+I28 -> 145.67221 | J30: =J26+J28 -> 189.66996
A32: balance check | D32: - | E32: - | F32: =F15-F30 -> -0.1 | G32: =G15-G30 -> -0.1 | H32: =H15-H30 -> -0.1 | I32: =I15-I30 -> -0.1 | J32: =J15-J30 -> -0.1

Sheet CFS
A1: EXCEL MODELING TEST
A2: Cash Flow Statement
A3: (INR, Millions)
E4: 2025 | F4: 2026 | G4: 2027 | H4: 2028 | I4: 2029
A6: Cash From Operations
A7: Net Profit | E7: =INC!F53 -> 5.8958162 | F7: =INC!G53 -> 11.690635 | G7: =INC!H53 -> 19.746085 | H7: =INC!I53 -> 30.963827 | I7: =INC!J53 -> 44.974345
A8: Add: Depreciation | E8: =INC!F42 -> 2.745 | F8: =INC!G42 -> 2.70825 | G8: =INC!H42 -> 2.6020125 | H8: =INC!I42 -> 2.0617106 | I8: =INC!J42 -> 2.352454
A9: Add: Provision | E9: =INC!F44 -> 1.503402 | F9: =INC!G44 -> 1.8217628 | G9: =INC!H44 -> 2.2257573 | H9: =INC!I44 -> 2.7415993 | I9: =INC!J44 -> 3.404409
A10: Less: cash paid for warranty service | E10: =0 -> 0 | F10: =0 -> 0 | G10: =0 -> 0 | H10: =-2 -> -2 | I10: =-3 -> -3
A11: (Increase)/Decrease in Receivables | E11: =BS!E7-BS!F7 -> -1.1702093 | F11: =BS!F7-BS!G7 -> -1.4760131 | G11: =BS!G7-BS!H7 -> -1.8730362 | H11: =BS!H7-BS!I7 -> -2.3915937 | I11: =BS!I7-BS!J7 -> -3.0729785
A12: (Increase)/Decrease in Inventory | E12: =BS!E8-BS!F8 -> -6.335271 | F12: =BS!F8-BS!G8 -> -7.9908294 | G12: =BS!G8-BS!H8 -> -10.14023 | H12: =BS!H8-BS!I8 -> -12.947593 | I12: =BS!I8-BS!J8 -> -16.63647
A13: (Increase)/Decrease in Other Current Assets | E13: =BS!E9-BS!F9 -> -1.1500333 | F13: =BS!F9-BS!G9 -> -1.4505646 | G13: =BS!G9-BS!H9 -> -1.8407424 | H13: =BS!H9-BS!I9 -> -2.3503593 | I13: =BS!I9-BS!J9 -> -3.0199961
A14: Increase/(Decrease in Accounts Payable | E14: =BS!F18-BS!E18 -> 0.96844907 | F14: =BS!G18-BS!F18 -> 1.2215281 | G14: =BS!H18-BS!G18 -> 1.5500989 | H14: =BS!I18-BS!H18 -> 1.9792499 | I14: =BS!J18-BS!I18 -> 2.5431546
A15: Increase/(Decrease in Other CL | E15: =BS!F19-BS!E19 -> 0.50440056 | F15: =BS!G19-BS!F19 -> 0.63621253 | G15: =BS!H19-BS!G19 -> 0.80734317 | H15: =BS!I19-BS!H19 -> 1.0308593 | I15: =BS!J19-BS!I19 -> 1.3245597
A17: Cash From Operations | E17: =SUM(E7:E15) -> 2.9615542 | F17: =SUM(F7:F15) -> 7.1609809 | G17: =SUM(G7:G15) -> 13.077288 | H17: =SUM(H7:H15) -> 19.0877 | I17: =SUM(I7:I15) -> 28.869478
A19: Cash (Used) in Investing Activities
A20: Capital Expenditures | E20: -2.5 | F20: -2 | G20: 1 | H20: -4 | I20: -5.5
A21: Investment in Subsidiary | E21: =-BS!F14 -> -5 | F21: =BS!F14-BS!G14 -> 0 | G21: =BS!G14-BS!H14 -> 2 | H21: =BS!H14-BS!I14 -> 0 | I21: =BS!I14-BS!J14 -> 3
A26: Cash (Used) in Investing Activities | E26: =SUM(E20:E21) -> -7.5 | F26: =SUM(F20:F21) -> -2 | G26: =SUM(G20:G21) -> 3 | H26: =SUM(H20:H21) -> -4 | I26: =SUM(I20:I21) -> -2.5
A29: Cash (Used) in Financing Activities
A30: Debt | E30: =10 -> 10 | F30: =0 -> 0 | G30: =0 -> 0 | H30: =0 -> 0 | I30: =0 -> 0
A31: Debt Repaid | E31: =0 -> 0 | F31: =-3 -> -3 | G31: =-3 -> -3 | H31: =-3 -> -3 | I31: =-3 -> -3
A32: Dividend Paid | E32: =-INC!F54 -> -0.29479081 | F32: =-INC!G54 -> -0.58453173 | G32: =-INC!H54 -> -0.98730423 | H32: =-INC!I54 -> -1.5481914 | I32: =-INC!J54 -> -2.2487172
A36: Cash (Used) in Financing Activities | E36: =SUM(E30:E32) -> 9.7052092 | F36: =SUM(F30:F32) -> -3.5845317 | G36: =SUM(G30:G32) -> -3.9873042 | H36: =SUM(H30:H32) -> -4.5481914 | I36: =SUM(I30:I32) -> -5.2487172
A39: Net Cash Flow | E39: =E17+E26+E36 -> 5.1667634 | F39: =F17+F26+F36 -> 1.5764491 | G39: =G17+G26+G36 -> 12.089983 | H39: =H17+H26+H36 -> 10.539509 | I39: =I17+I26+I36 -> 21.120761
A41: Beginning Cash Balance | E41: =BS!E6 -> 1 | F41: =E42 -> 6.1667634 | G41: =F42 -> 7.7432126 | H41: =G42 -> 19.833196 | I41: =H42 -> 30.372705
A42: Ending Cash Balance | E42: =E41+E39 -> 6.1667634 | F42: =F41+F39 -> 7.7432126 | G42: =G41+G39 -> 19.833196 | H42: =H41+H39 -> 30.372705 | I42: =I41+I39 -> 51.493465

Sheet RATIOS
A1: EXCEL MODELING TEST
A2: Key Ratios
A3: (INR, Millions)
B4: 2025 | C4: 2026 | D4: 2027 | E4: 2028 | F4: 2029
A6: Net Sales Growth % | B6: =INC!F30 -> 0.20176022 | C6: =INC!G30 -> 0.21176022 | D6: =INC!H30 -> 0.22176022 | E6: =INC!I30 -> 0.23176022 | F6: =INC!J30 -> 0.24176022
A7: Gross Profit Margin | B7: =INC!F33/INC!F29 -> 0.35710086 | C7: =INC!G33/INC!G29 -> 0.3683358 | D7: =INC!H33/INC!H29 -> 0.37693474 | E7: =INC!I33/INC!I29 -> 0.38572714 | F7: =INC!J33/INC!J29 -> 0.39469667
A8: EBIT Margin | B8: =INC!F46/INC!F29 -> 0.064165102 | C8: =INC!G46/INC!G29 -> 0.10168671 | D8: =INC!H46/INC!H29 -> 0.13412375 | E8: =INC!I46/INC!I29 -> 0.16558962 | F8: =INC!J46/INC!J29 -> 0.19161348
A9: Net Profit Margin | B9: =INC!F53/INC!F29 -> 0.039216497 | C9: =INC!G53/INC!G29 -> 0.064172101 | D9: =INC!H53/INC!H29 -> 0.088716252 | E9: =INC!I53/INC!I29 -> 0.11294075 | F9: =INC!J53/INC!J29 -> 0.13210617
A10: Interest Coverage Ratio | B10: =INC!F46/INC!F48 -> 7.8812047 | C10: =INC!G46/INC!G48 -> 10.156199 | D10: =INC!H46/INC!H48 -> 18.158572 | E10: =INC!I46/INC!I48 -> 39.001752 | F10: =INC!J46/INC!J48 -> 66.293764
A11: Debt Service Coverage Ratio | B11: =INC!F40/(INC!F48-CFS!E31) -> 11.352121 | C11: =INC!G40/(INC!G48-CFS!F31) -> 4.7792121 | D11: =INC!H40/(INC!H48-CFS!G31) -> 7.4677998 | E11: =INC!I40/(INC!I48-CFS!H31) -> 12.05604 | F11: =INC!J40/(INC!J48-CFS!I31) -> 17.818757
A12: Retention Ratio | B12: =(INC!F53-INC!F54)/INC!F53 -> 0.95 | C12: =(INC!G53-INC!G54)/INC!G53 -> 0.95 | D12: =(INC!H53-INC!H54)/INC!H53 -> 0.95 | E12: =(INC!I53-INC!I54)/INC!I53 -> 0.95 | F12: =(INC!J53-INC!J54)/INC!J53 -> 0.95
A13: Current Ratio | B13: =BS!F10/BS!F20 -> 6.5796497 | C13: =BS!G10/BS!G20 -> 6.605102 | D13: =BS!H10/BS!H20 -> 7.4037486 | E13: =BS!I10/BS!I20 -> 7.7752269 | F13: =BS!J10/BS!J20 -> 8.4687711
A14: Receivable Days | B14: =BS!F7/INC!F29*365 -> 16.922462 | C14: =BS!G7/INC!G29*365 -> 16.922462 | D14: =BS!H7/INC!H29*365 -> 16.922462 | E14: =BS!I7/INC!I29*365 -> 16.922462 | F14: =BS!J7/INC!J29*365 -> 16.922462
A15: Debt Equity | B15: =(BS!F22+BS!F23)/BS!F28 -> 0.71696379 | C15: =(BS!G22+BS!G23)/BS!G28 -> 0.5120813 | D15: =(BS!H22+BS!H23)/BS!H28 -> 0.25108098 | E15: =(BS!I22+BS!I23)/BS!I28 -> 0.15372856 | F15: =(BS!J22+BS!J23)/BS!J28 -> 0.089687796
A16: Book Value (INR million) | B16: =BS!F28 -> 42.401025 | C16: =BS!G28 -> 53.507128 | D16: =BS!H28 -> 77.265909 | E16: =BS!I28 -> 106.68154 | F16: =BS!J28 -> 149.40717
A17: Return on Capital Employed | B17: =INC!F46/(BS!F28+BS!F22+BS!F23) -> 0.1325063 | C17: =INC!G46/(BS!G28+BS!G22+BS!G23) -> 0.22896507 | D17: =INC!H46/(BS!H28+BS!H22+BS!H23) -> 0.30882338 | E17: =INC!I46/(BS!I28+BS!I22+BS!I23) -> 0.36884522 | F17: =INC!J46/(BS!J28+BS!J22+BS!J23) -> 0.40067684
A18: Return on Equity | B18: =INC!F53/BS!F28 -> 0.13904891 | C18: =INC!G53/BS!G28 -> 0.21848742 | D18: =INC!H53/BS!H28 -> 0.25556012 | E18: =INC!I53/BS!I28 -> 0.2902454 | F18: =INC!J53/BS!J28 -> 0.30101865

Sheet FCFF Valuation
A1: EXCEL MODELING TEST
A2: FCFF Valuation
A3: (INR, Millions)
F4: 2025 | G4: 2026 | H4: 2027 | I4: 2028 | J4: 2029
A7: Beta to beused for stock | B7: 1.2
A8: Riskfree rate (Rf) | B8: 0.0325
A9: Market Rate of Return (Rm) | B9: 0.103
A10: Growth Rate | B10: 0.03
A12: Cost of Equity (CAPM) | B12: =B8+B7*(B9-B8) -> 0.1171
A13: Pre-tax Cost of Debt | B13: =6% -> 0.06
A14: Tax Rate | B14: =30% -> 0.3
A15: After-tax Cost of Debt | B15: =B13*(1-B14) -> 0.042
A16: Weight of Equity | B16: =BS!F28/(BS!F28+BS!F22+BS!F23) -> 0.58242346
A17: Weight of Debt | B17: =1-B16 -> 0.41757654
A18: WACC | B18: =B16*B12+B17*B15 -> 0.085740002
A21: EBIT | F21: =INC!F46 -> 9.6465945 | G21: =INC!G46 -> 18.524906 | H21: =INC!H46 -> 29.852692 | I21: =INC!I46 -> 45.398039 | J21: =INC!J46 -> 65.233064
A22: Less: Tax on EBIT | F22: =F21*$B$14 -> 2.8939784 | G22: =G21*$B$14 -> 5.5574719 | H22: =H21*$B$14 -> 8.9558077 | I22: =I21*$B$14 -> 13.619412 | J22: =J21*$B$14 -> 19.569919
A23: NOPAT | F23: =F21-F22 -> 6.7526162 | G23: =G21-G22 -> 12.967435 | H23: =H21-H22 -> 20.896885 | I23: =I21-I22 -> 31.778627 | J23: =J21-J22 -> 45.663145
A24: Add: Depreciation | F24: =INC!F42 -> 2.745 | G24: =INC!G42 -> 2.70825 | H24: =INC!H42 -> 2.6020125 | I24: =INC!I42 -> 2.0617106 | J24: =INC!J42 -> 2.352454
A25: Less: Capital Expenditure | F25: =-CFS!E20 -> 2.5 | G25: =-CFS!F20 -> 2 | H25: =-CFS!G20 -> -1 | I25: =-CFS!H20 -> 4 | J25: =-CFS!I20 -> 5.5
A26: Less: Increase in Net Working Capital | F26: =((BS!F7+BS!F8+BS!F9)-(BS!F18+BS!F19))-((BS!E7+BS!E8+BS!E9)-(BS!E18+BS!E19)) -> 7.1826639 | G26: =((BS!G7+BS!G8+BS!G9)-(BS!G18+BS!G19))-((BS!F7+BS!F8+BS!F9)-(BS!F18+BS!F19)) -> 9.0596665 | H26: =((BS!H7+BS!H8+BS!H9)-(BS!H18+BS!H19))-((BS!G7+BS!G8+BS!G9)-(BS!G18+BS!G19)) -> 11.496567 | I26: =((BS!I7+BS!I8+BS!I9)-(BS!I18+BS!I19))-((BS!H7+BS!H8+BS!H9)-(BS!H18+BS!H19)) -> 14.679437 | J26: =((BS!J7+BS!J8+BS!J9)-(BS!J18+BS!J19))-((BS!I7+BS!I8+BS!I9)-(BS!I18+BS!I19)) -> 18.86173
A27: Free Cash Flow to Firm (FCFF) | F27: =F23+F24-F25-F26 -> -0.18504779 | G27: =G23+G24-G25-G26 -> 4.6160181 | H27: =H23+H24-H25-H26 -> 13.00233 | I27: =I23+I24-I25-I26 -> 15.160901 | J27: =J23+J24-J25-J26 -> 23.653869
A28: Discount Factor | F28: =1/(1+$B$18)^1 -> 0.92103082 | G28: =1/(1+$B$18)^2 -> 0.84829776 | H28: =1/(1+$B$18)^3 -> 0.78130838 | I28: =1/(1+$B$18)^4 -> 0.7196091 | J28: =1/(1+$B$18)^5 -> 0.66278215
A29: PV of FCFF | F29: =F27*F28 -> -0.17043472 | G29: =G27*G28 -> 3.9157578 | H29: =H27*H28 -> 10.15883 | I29: =I27*I28 -> 10.909922 | J29: =J27*J28 -> 15.677362
A31: Terminal Value (end of 2029) | J31: =J27*(1+$B$10)/($B$18-$B$10) -> 437.09157
A32: PV of Terminal Value | J32: =J31*J28 -> 289.69649
A34: Sum of PV of FCFF (2025-2029) | B34: =SUM(F29:J29) -> 40.491437
A35: PV of Terminal Value | B35: =J32 -> 289.69649
A36: Enterprise Value | B36: =B34+B35 -> 330.18793
A37: Less: Net Debt (as of 2024) | B37: =BS!E22+BS!E23-BS!E6 -> 19.4
A38: Equity Value | B38: =B36-B37 -> 310.78793

Sheet Instruction
A1: Income Statement | G1: Working Capital and Balance Sheet
A3: Net Sales
A4: For 2025 - Sales grows by the CAGR of 2007-10 plus - | E4: 0.02 | G4: Working capital: Use the same proportions as a percentage
A5: For 2026 to 2029 - Sales grows at previous year's growth plus - | E5: 0.01 | G5: of revenues as observed in previous year
G6: Other Long-term Assets: Keep flat.
A7: Cost of Goods Sold (COGS) | G7: Other Long-term Liabilities: Keep flat.
A8: C O G S Growth /Net Sales Growth ('11 & '12) | E8: 0.9 | G8: Debt: Company takes additional debt of US$10 million in 2025 & repays US$3 million every year from 2026 to 29
A9: (ie, if sales grows by 100%, COGS grows by90%) | G9: Convertible bond gets converted at the year mentioned with it
A10: C O G S growth /Net Sales Growth ('13 to '15) | E10: 0.925 | G10: Dividend Payout ratio as % of net income | K10: 0.05
A11: (ie, if sales grows by 100%, COGS grows by 92.5%) | G11: Investment in subsidiary: The company would buy controlling stake in a company in 2025
G12: for US$5 mn. It would sell 40% of it at cost in 2027 and remaining stake in 2029 at cost.
A13: SG&A
A14: Fixed SG&A growth rate/Net Sales Growth | E14: 0.25
A15: (ie, if sales grows by 10%, fixed SG&A grows by 2.5%)
A17: Variable SG&A as % of Net Sales | E17: 0.09
A19: Depreciation on Opening Net Block | E19: 0.15
A21: Provision for warranty (as a % of Net Sales) | E21: 0.01
A23: Warranty service: The company is expected to incur the following
A24: cash expenditure for repair of products under warranty
A25: 2028 | E25: INR 2.0 mn
A26: 2029 | E26: INR 3.0 mn
A28: Tax Rate (every year) | E28: 0.3
A31: Interest Expense (on debt + convertible bond)
A33: Condition 1:
A34: Use beginning of year balance to calculate interest expense at | E34: 0.06
A35: Condition 2:
A36: If Interest coverage falls below 6 times, calculate interest expense
A37: for next year at | E37: 0.07
