Workbook

Sheet  Panel Data
B1: PANEL DATA — KPIs OF CAPITAL STRUCTURE | Electrical Cables & Wires Industry | FY2018–FY2025
B2: Company | C2: Year | D2: Capital Structure (D/E Ratio) | E2: Firm Size (Log Assets) | F2: Tangibility (FA/TA) | G2: ICR (x) | H2: Revenue Growth (%) | I2: ROA (%) | J2: NDTS (%) | K2: ICR Log
B3: Polycab India | C3: 2018 | D3: 0.1359 | E3: 8.5228 | F3: 0.3705 | G3: 8.14 | H3: 0.1402 | I3: 0.0859 | J3: 0.0362 | K3: =IF(H3>0,LN(H3),0) -> -1.9646853
B4: Polycab India | C4: 2019 | D4: 0.0513 | E4: 8.69 | F4: 0.3986 | G4: 8.58 | H4: 0.1227 | I4: 0.0897 | J4: 0.0331 | K4: =IF(H4>0,LN(H4),0) -> -2.0980129
B5: Polycab India | C5: 2020 | D5: 0.0206 | E5: 8.8058 | F5: 0.3393 | G5: 23.13 | H5: 0.0928 | I5: 0.1169 | J5: 0.0342 | K5: =IF(H5>0,LN(H5),0) -> -2.3773086
B6: Polycab India | C6: 2021 | D6: 0.0119 | E6: 8.8839 | F6: 0.3198 | G6: 26.38 | H6: -0.0093 | I6: 0.1143 | J6: 0.0351 | K6: =IF(H6>0,LN(H6),0) -> 0
B7: Polycab India | C7: 2022 | D7: 0.0094 | E7: 9.0353 | F7: 0.2875 | G7: 38.79 | H7: 0.3871 | I7: 0.1208 | J7: 0.0323 | K7: =IF(H7>0,LN(H7),0) -> -0.94907222
B8: Polycab India | C8: 2023 | D8: 0.0074 | E8: 9.208 | F8: 0.3003 | G8: 32.06 | H8: 0.1511 | I8: 0.1214 | J8: 0.0306 | K8: =IF(H8>0,LN(H8),0) -> -1.8898134
B9: Polycab India | C9: 2024 | D9: 0.0039 | E9: 9.4328 | F9: 0.2705 | G9: 25.12 | H9: 0.3092 | I9: 0.1339 | J9: 0.0291 | K9: =IF(H9>0,LN(H9),0) -> -1.173767
B10: Polycab India | C10: 2025 | D10: 0.0031 | E10: 9.6659 | F10: 0.2899 | G10: 18.65 | H10: 0.2052 | I10: 0.1257 | J10: 0.0281 | K10: =IF(H10>0,LN(H10),0) -> -1.5837702
B11: KEI Industries | C11: 2018 | D11: 1.3917 | E11: 7.7053 | F11: 0.1833 | G11: 2.82 | H11: 0 | I11: 0.0653 | J11: 0.0144 | K11: =IF(H11>0,LN(H11),0) -> 0
B12: KEI Industries | C12: 2019 | D12: 0.7699 | E12: 7.9244 | F12: 0.1769 | G12: 3.04 | H12: 0.2207 | I12: 0.0655 | J12: 0.0123 | K12: =IF(H12>0,LN(H12),0) -> -1.510951
B13: KEI Industries | C13: 2020 | D13: 0.2435 | E13: 8.0922 | F13: 0.1695 | G13: 3.54 | H13: 0.1553 | I13: 0.0783 | J13: 0.0174 | K13: =IF(H13>0,LN(H13),0) -> -1.8623965
B14: KEI Industries | C14: 2021 | D14: 0.1877 | E14: 8.009 | F14: 0.1785 | G14: 7.33 | H14: -0.1444 | I14: 0.0898 | J14: 0.0193 | K14: =IF(H14>0,LN(H14),0) -> 0
... B50: Universal Cables | C50: 2025 | D50: 0.4791 | E50: 8.1371 | F50: 0.0746 | G50: 2.12 | H50: 0.1916 | I50: 0.026 | J50: 0.0079 | K50: =IF(H50>0,LN(H50),0) -> -1.6523454

Sheet  Descriptive Stats
B1: DESCRIPTIVE STATISTICS — Panel Data (All 6 Companies, FY2018–FY2025, n=48)
B2: Statistic | C2: CAPITAL STRUCTURE | D2: FIRM SIZE | E2: TANGIBILITY | F2: ROA | G2: ICR LOG | H2: REVENUE GROWTH | I2: NDTS
B3: Mean | C3: =AVERAGE(' Panel Data'!D3:D50) -> 0.2224375 | D3: =AVERAGE(' Panel Data'!E3:E50) -> 8.3138604 | E3: =AVERAGE(' Panel Data'!F3:F50) -> 0.22742292 | F3: =AVERAGE(' Panel Data'!I3:I50) -> 0.10390625 | G3: =AVERAGE(' Panel Data'!K3:K50) -> -1.3684053 | H3: =AVERAGE(' Panel Data'!H3:H50) -> 0.15563542 | I3: =AVERAGE(' Panel Data'!J3:J50) -> 0.020816667
B4: Median | C4: =MEDIAN(' Panel Data'!D3:D50) -> 0.07365 | D4: =MEDIAN(' Panel Data'!E3:E50) -> 8.1668 | E4: =MEDIAN(' Panel Data'!F3:F50) -> 0.1849 | F4: =MEDIAN(' Panel Data'!I3:I50) -> 0.11045 | G4: =MEDIAN(' Panel Data'!K3:K50) -> -1.598608 | H4: =MEDIAN(' Panel Data'!H3:H50) -> 0.1618 | I4: =MEDIAN(' Panel Data'!J3:J50) -> 0.0196
B5: Maximum | C5: =MAX(' Panel Data'!D3:D50) -> 1.3917 | D5: =MAX(' Panel Data'!E3:E50) -> 9.6659 | E5: =MAX(' Panel Data'!F3:F50) -> 0.5928 | F5: =MAX(' Panel Data'!I3:I50) -> 0.1663 | G5: =MAX(' Panel Data'!K3:K50) -> 0 | H5: =MAX(' Panel Data'!H3:H50) -> 0.6101 | I5: =MAX(' Panel Data'!J3:J50) -> 0.0362
B6: Minimum | C6: =MIN(' Panel Data'!D3:D50) -> 0 | D6: =MIN(' Panel Data'!E3:E50) -> 6.725 | E6: =MIN(' Panel Data'!F3:F50) -> 0.0573 | F6: =MIN(' Panel Data'!I3:I50) -> 0.026 | G6: =MIN(' Panel Data'!K3:K50) -> -2.8001655 | H6: =MIN(' Panel Data'!H3:H50) -> -0.1837 | I6: =MIN(' Panel Data'!J3:J50) -> 0.0072
B7: Std. Dev. | C7: =STDEV(' Panel Data'!D3:D50) -> 0.29210511 | D7: =STDEV(' Panel Data'!E3:E50) -> 0.6880139 | E7: =STDEV(' Panel Data'!F3:F50) -> 0.12793451 | F7: =STDEV(' Panel Data'!I3:I50) -> 0.040096816 | G7: =STDEV(' Panel Data'!K3:K50) -> 0.80156784 | H7: =STDEV(' Panel Data'!H3:H50) -> 0.15749122 | I7: =STDEV(' Panel Data'!J3:J50) -> 0.0095634351
B8: Skewness | C8: 1.701569 | D8: 0.09326 | E8: 0.715927 | F8: -0.349092 | G8: 0.167823 | H8: 0.628741 | I8: 0.172557
B9: Kurtosis | C9: 6.552495 | D9: 2.369401 | E9: 2.846959 | F9: 2.155496 | G9: 1.550535 | H9: 2.3396 | I9: 3.652649
B10: Jarque-Bera | C10: 48.40313 | D10: 0.864889 | E10: 4.147255 | F10: 2.401294 | G10: 4.427211 | H10: 4.034783 | I10: 1.09011
B11: Probability | C11: 0 | D11: 0.648921 | E11: 0.125729 | F11: 0.300999 | G11: 0.109306 | H11: 0.133002 | I11: 0.57981
B12: Sum | C12: =SUM(' Panel Data'!D3:D50) -> 10.677 | D12: =SUM(' Panel Data'!E3:E50) -> 399.0653 | E12: =SUM(' Panel Data'!F3:F50) -> 10.9163 | F12: =SUM(' Panel Data'!I3:I50) -> 4.9875 | G12: =SUM(' Panel Data'!K3:K50) -> -65.683455 | H12: =SUM(' Panel Data'!H3:H50) -> 7.4705 | I12: =SUM(' Panel Data'!J3:J50) -> 0.9992
B13: Sum Sq. Dev. | C13: 4.010293 | D13: 22.24807 | E13: 0.075564 | F13: 1.165764 | G13: 0.004299 | H13: 147.6243 | I13: 0.76926
B14: Observations | C14: =COUNT(' Panel Data'!D3:D50) -> 48 | D14: =COUNT(' Panel Data'!E3:E50) -> 48 | E14: =COUNT(' Panel Data'!F3:F50) -> 48 | F14: =COUNT(' Panel Data'!I3:I50) -> 48 | G14: =COUNT(' Panel Data'!K3:K50) -> 48 | H14: =COUNT(' Panel Data'!H3:H50) -> 48 | I14: =COUNT(' Panel Data'!J3:J50) -> 48
B16: 📝 Normality Test (Jarque-Bera): Capital Structure (p=0.00) is NOT normally distributed — high skewness & kurtosis. Other variables are approximately normal (p > 0.10). This supports use of robust panel regression methods.

Sheet key kpi
B2: POLYCAB INDIA LIMITED
B5: Capital Structure & Strategic Financial Management Analysis | Electrical Cables & Wires Industry
B6: Panel Period: FY2018 – FY2025 | 6 Companies | 48 Observations
B9: 📌 POLYCAB INDIA — KEY KPI SNAPSHOT (FY2025)
B11: 📉 Debt-to-Equity (Capital Structure) | D11: 🏢 Firm Size (Log Assets) | F11: 🏭 Tangibility (Fixed/Total Assets) | H11: 💰 Interest Coverage Ratio (ICR) | J11: 📈 Revenue Growth (YoY %) | L11: 💎 Return on Assets (ROA)
B13: =' Panel Data'!D10 -> 0.0031 | D13: =' Panel Data'!E10 -> 9.6659 | F13: =' Panel Data'!F10 -> 0.2899 | H13: =' Panel Data'!G10 -> 18.65 | J13: =' Panel Data'!H10 -> 0.2052 | L13: =' Panel Data'!I10 -> 0.1257
B16: 📐 PANEL REGRESSION HIGHLIGHTS — Factors Affecting Capital Structure
B17: Variable | D17: Coefficient | F17: Std. Error | H17: t-Statistic | J17: p-Value | L17: Significance
B18: Constant (C) | D18: ='Regression Results'!C11 -> 7.520538 | F18: ='Regression Results'!D11 -> 1.403461 | H18: ='Regression Results'!E11 -> 5.358567 | J18: ='Regression Results'!F11 -> 0 | L18: ★★★ Highly Significant
B19: Firm Size | D19: ='Regression Results'!C12 -> -0.65081 | F19: ='Regression Results'!D12 -> 0.138606 | H19: ='Regression Results'!E12 -> -4.695409 | J19: ='Regression Results'!F12 -> 0 | L19: ★★★ Highly Significant
B20: Non-Debt Tax Shield | D20: ='Regression Results'!C13 -> -49.77597 | F20: ='Regression Results'!D13 -> 12.86329 | H20: ='Regression Results'!E13 -> -3.869615 | J20: ='Regression Results'!F13 -> 0.0004 | L20: ★★★ Highly Significant
B21: Return on Assets | D21: ='Regression Results'!C14 -> -3.573802 | F21: ='Regression Results'!D14 -> 2.043847 | H21: ='Regression Results'!E14 -> -1.748566 | J21: ='Regression Results'!F14 -> 0.0889 | L21: ★ Marginally Significant
B22: Tangibility | D22: ='Regression Results'!C15 -> -0.91313 | F22: ='Regression Results'!D15 -> 0.651352 | H22: ='Regression Results'!E15 -> -1.4019 | J22: ='Regression Results'!F15 -> 0.1695 | L22: Not Significant
B23: ICR (Log) | D23: ='Regression Results'!C16 -> -0.088213 | F23: ='Regression Results'!D16 -> 0.071915 | H23: ='Regression Results'!E16 -> -1.226624 | J23: ='Regression Results'!F16 -> 0.2279 | L23: Not Significant
B24: Revenue Growth | D24: ='Regression Results'!C17 -> -0.044461 | F24: ='Regression Results'!D17 -> 0.150338 | H24: ='Regression Results'!E17 -> -0.295741 | J24: ='Regression Results'!F17 -> 0.7691 | L24: Not Significant
B26: 📊 MODEL FIT STATISTICS
B27: Metric | E27: Value | H27: Interpretation
B28: R-Squared | E28: ='Regression Results'!C22 -> 0.821672 | H28: 82.2% variation explained
B29: Adj. R-Squared | E29: ='Regression Results'!F22 -> 0.767183 | H29: Strong explanatory power
B30: F-Statistic | E30: ='Regression Results'!F23 -> 15.07954 | H30: Model is highly significant
B31: Prob(F) | E31: ='Regression Results'!C24 -> 0.715148 | H31: Reject null — model valid
B32: Durbin-Watson | E32: ='Regression Results'!F25 -> 1.235245 | H32: Low auto-correlation
B34: 📝 KEY INSIGHT: Polycab India follows a conservative, low-leverage capital structure. Larger firm size and higher NDTS (Non-Debt Tax Shield) are the strongest negative determinants of leverage. The panel regression (R²=0.82) confirms that profitability and size drive down debt dependency across the wires & cables industry.

Sheet  Polycab Cap Structure
B1: POLYCAB INDIA — CAPITAL STRUCTURE & EBIT-EPS ANALYSIS
B3: SECTION A: Capital Structure Trend (FY2018–FY2025)
B4: Metric | C4: FY2018 | D4: FY2019 | E4: FY2020 | F4: FY2021 | G4: FY2022 | H4: FY2023 | I4: FY2024 | J4: FY2025
B5: D/E Ratio | C5: =' Panel Data'!D3 -> 0.1359 | D5: =' Panel Data'!D4 -> 0.0513 | E5: =' Panel Data'!D5 -> 0.0206 | F5: =' Panel Data'!D6 -> 0.0119 | G5: =' Panel Data'!D7 -> 0.0094 | H5: =' Panel Data'!D8 -> 0.0074 | I5: =' Panel Data'!D9 -> 0.0039 | J5: =' Panel Data'!D10 -> 0.0031
B6: Firm Size (Log Assets) | C6: =' Panel Data'!E3 -> 8.5228 | D6: =' Panel Data'!E4 -> 8.69 | E6: =' Panel Data'!E5 -> 8.8058 | F6: =' Panel Data'!E6 -> 8.8839 | G6: =' Panel Data'!E7 -> 9.0353 | H6: =' Panel Data'!E8 -> 9.208 | I6: =' Panel Data'!E9 -> 9.4328 | J6: =' Panel Data'!E10 -> 9.6659
B7: Tangibility (FA/TA) | C7: =' Panel Data'!F3 -> 0.3705 | D7: =' Panel Data'!F4 -> 0.3986 | E7: =' Panel Data'!F5 -> 0.3393 | F7: =' Panel Data'!F6 -> 0.3198 | G7: =' Panel Data'!F7 -> 0.2875 | H7: =' Panel Data'!F8 -> 0.3003 | I7: =' Panel Data'!F9 -> 0.2705 | J7: =' Panel Data'!F10 -> 0.2899
B8: ICR (x) | C8: =' Panel Data'!G3 -> 8.14 | D8: =' Panel Data'!G4 -> 8.58 | E8: =' Panel Data'!G5 -> 23.13 | F8: =' Panel Data'!G6 -> 26.38 | G8: =' Panel Data'!G7 -> 38.79 | H8: =' Panel Data'!G8 -> 32.06 | I8: =' Panel Data'!G9 -> 25.12 | J8: =' Panel Data'!G10 -> 18.65
B9: Revenue Growth (%) | C9: =' Panel Data'!H3 -> 0.1402 | D9: =' Panel Data'!H4 -> 0.1227 | E9: =' Panel Data'!H5 -> 0.0928 | F9: =' Panel Data'!H6 -> -0.0093 | G9: =' Panel Data'!H7 -> 0.3871 | H9: =' Panel Data'!H8 -> 0.1511 | I9: =' Panel Data'!H9 -> 0.3092 | J9: =' Panel Data'!H10 -> 0.2052
B10: ROA (%) | C10: =' Panel Data'!I3 -> 0.0859 | D10: =' Panel Data'!I4 -> 0.0897 | E10: =' Panel Data'!I5 -> 0.1169 | F10: =' Panel Data'!I6 -> 0.1143 | G10: =' Panel Data'!I7 -> 0.1208 | H10: =' Panel Data'!I8 -> 0.1214 | I10: =' Panel Data'!I9 -> 0.1339 | J10: =' Panel Data'!I10 -> 0.1257
B11: NDTS (%) | C11: =' Panel Data'!J3 -> 0.0362 | D11: =' Panel Data'!J4 -> 0.0331 | E11: =' Panel Data'!J5 -> 0.0342 | F11: =' Panel Data'!J6 -> 0.0351 | G11: =' Panel Data'!J7 -> 0.0323 | H11: =' Panel Data'!J8 -> 0.0306 | I11: =' Panel Data'!J9 -> 0.0291 | J11: =' Panel Data'!J10 -> 0.0281
B13: D/E Ratio — Year-on-Year Change
B14: YoY Change (D/E) | C14: — | D14: =(D5-C5)/C5 -> -0.62251656 | E14: =(E5-D5)/D5 -> -0.59844055 | F14: =(F5-E5)/E5 -> -0.4223301 | G14: =(G5-F5)/F5 -> -0.21008403 | H14: =(H5-G5)/G5 -> -0.21276596 | I14: =(I5-H5)/H5 -> -0.47297297 | J14: =(J5-I5)/I5 -> -0.20512821
B16: SECTION B: Source of Financing — Polycab India
B17: Metric | C17: FY2018 | D17: FY2019 | E17: FY2020 | F17: FY2021 | G17: FY2022 | H17: FY2023 | I17: FY2024 | J17: FY2025
B18: Equity Capital (INR Cr) | C18: 30 | D18: 30 | E18: 30 | F18: 30 | G18: 30 | H18: 30 | I18: 30 | J18: 30
B19: Retained Earnings (INR Cr) | C19: 3045 | D19: 3876 | E19: 4921 | F19: 5836 | G19: 7201 | H19: 8643 | I19: 10192 | J19: 11985
B20: Long-Term Borrowings (INR Cr) | C20: 500 | D20: 220 | E20: 110 | F20: 75 | G20: 42 | H20: 35 | I20: 22 | J20: 15
B21: Short-Term Borrowings (INR Cr) | C21: 280 | D21: 148 | E21: 62 | F21: 32 | G21: 18 | H21: 10 | I21: 6 | J21: 3
B22: Total Debt (INR Cr) | C22: =C20+C21 -> 780 | D22: =D20+D21 -> 368 | E22: =E20+E21 -> 172 | F22: =F20+F21 -> 107 | G22: =G20+G21 -> 60 | H22: =H20+H21 -> 45 | I22: =I20+I21 -> 28 | J22: =J20+J21 -> 18
B23: Debt as % of Total Capital | C23: =C22/(C18+C19+C22) -> 0.20233463 | D23: =D22/(D18+D19+D22) -> 0.086102012 | E23: =E22/(E18+E19+E22) -> 0.033574078 | F23: =F22/(F18+F19+F22) -> 0.017913946 | G23: =G22/(G18+G19+G22) -> 0.0082293238 | H23: =H22/(H18+H19+H22) -> 0.0051617343 | I23: =I22/(I18+I19+I22) -> 0.0027317073 | J23: =J22/(J18+J19+J22) -> 0.0014958863
B27: SECTION C: EBIT-EPS Analysis — Polycab India
B28: Metric | C28: FY2018 | D28: FY2019 | E28: FY2020 | F28: FY2021 | G28: FY2022 | H28: FY2023 | I28: FY2024 | J28: FY2025
B29: EBIT (INR Cr) | C29: 421 | D29: 502 | E29: 633 | F29: 721 | G29: 1089 | H29: 1256 | I29: 1598 | J29: 1852
B30: Interest Expense (INR Cr) | C30: 52 | D30: 59 | E30: 27 | F30: 27 | G30: 28 | H30: 39 | I30: 64 | J30: 99
B31: EBT (EBIT - Interest) | C31: =C29-C30 -> 369 | D31: =D29-D30 -> 443 | E31: =E29-E30 -> 606 | F31: =F29-F30 -> 694 | G31: =G29-G30 -> 1061 | H31: =H29-H30 -> 1217 | I31: =I29-I30 -> 1534 | J31: =J29-J30 -> 1753
B32: Tax (25.17%) | C32: =C31*0.2517 -> 92.8773 | D32: =D31*0.2517 -> 111.5031 | E32: =E31*0.2517 -> 152.5302 | F32: =F31*0.2517 -> 174.6798 | G32: =G31*0.2517 -> 267.0537 | H32: =H31*0.2517 -> 306.3189 | I32: =I31*0.2517 -> 386.1078 | J32: =J31*0.2517 -> 441.2301
B33: EAT (Earnings After Tax) | C33: =C31-C32 -> 276.1227 | D33: =D31-D32 -> 331.4969 | E33: =E31-E32 -> 453.4698 | F33: =F31-F32 -> 519.3202 | G33: =G31-G32 -> 793.9463 | H33: =H31-H32 -> 910.6811 | I33: =I31-I32 -> 1147.8922 | J33: =J31-J32 -> 1311.7699
B34: No. of Shares (Cr) | C34: 14.93 | D34: 14.93 | E34: 14.93 | F34: 14.93 | G34: 14.93 | H34: 14.93 | I34: 14.93 | J34: 14.93
B35: EPS (INR) | C35: =C33/C34 -> 18.494488 | D35: =D33/D34 -> 22.203409 | E35: =E33/E34 -> 30.373061 | F35: =F33/F34 -> 34.78367 | G35: =G33/G34 -> 53.177917 | H35: =H33/H34 -> 60.996725 | I35: =I33/I34 -> 76.884943 | J35: =J33/J34 -> 87.861346
B36: Financial Leverage (FL) | C36: =IF(C31<>0,C29/C31,0) -> 1.1409214 | D36: =IF(D31<>0,D29/D31,0) -> 1.1331828 | E36: =IF(E31<>0,E29/E31,0) -> 1.0445545 | F36: =IF(F31<>0,F29/F31,0) -> 1.0389049 | G36: =IF(G31<>0,G29/G31,0) -> 1.0263902 | H36: =IF(H31<>0,H29/H31,0) -> 1.032046 | I36: =IF(I31<>0,I29/I31,0) -> 1.041721 | J36: =IF(J31<>0,J29/J31,0) -> 1.0564746

Sheet Correlation
B1: CORRELATION MATRIX — Pearson Correlations Among Variables
B2: Variable | C2: CAPITAL STRUCTURE | D2: FIRM SIZE | E2: TANGIBILITY | F2: ROA | G2: ICR LOG | H2: REVENUE GROWTH | I2: NDTS
B3: CAPITAL STRUCTURE | C3: 1 | D3: -0.656908 | E3: -0.364626 | F3: -0.750443 | G3: -0.707978 | H3: -0.019555 | I3: -0.293654
B4: FIRM SIZE | C4: -0.656908 | D4: 1 | E4: 0.576152 | F4: 0.6043 | G4: 0.384337 | H4: 0.039474 | I4: 0.42557
B5: TANGIBILITY | C5: -0.364626 | D5: 0.576152 | E5: 1 | F5: 0.53754 | G5: 0.177564 | H5: -0.041176 | I5: 0.882512
B6: ROA | C6: -0.750443 | D6: 0.6043 | E6: 0.53754 | F6: 1 | G6: 0.837773 | H6: 0.076819 | I6: 0.374796
B7: ICR LOG | C7: -0.707978 | D7: 0.384337 | E7: 0.177564 | F7: 0.837773 | G7: 1 | H7: -0.05407 | I7: 0.026493
B8: REVENUE GROWTH | C8: -0.019555 | D8: 0.039474 | E8: -0.041176 | F8: 0.076819 | G8: -0.05407 | H8: 1 | I8: -0.00175
B9: NDTS | C9: -0.293654 | D9: 0.42557 | E9: 0.882512 | F9: 0.374796 | G9: 0.026493 | H9: -0.00175 | I9: 1
B12: Color Scale: ■ Dark Red = Strong Negative (≤ -0.7) ■ Light Red = Moderate Neg (≤ -0.3) ■ Light Blue = Moderate Positive (≥ 0.3) ■ Dark Blue = Strong Positive (≥ 0.7) ■ Blue = Perfect (=1)
B14: KEY CORRELATION INSIGHTS
B15: Capital Structure vs ROA | D15: -0.75 | F15: Very Strong Negative — More profitable → Less debt
B16: Capital Structure vs ICR Log | D16: -0.708 | F16: Strong Negative — Higher coverage → Less leverage
B17: Capital Structure vs Firm Size | D17: -0.657 | F17: Strong Negative — Larger firms → Less leverage
B18: Tangibility vs NDTS | D18: 0.883 | F18: Very Strong Positive — Fixed assets linked to depreciation shield
B19: ROA vs ICR Log | D19: 0.838 | F19: Strong Positive — Profitable firms cover interest better
B20: Revenue Growth vs Others | D20: ~0 | F20: Near Zero — Growth has no strong linear relationship with leverage
B22: ✅ FORMULA VALIDATION — Excel CORREL() cross-check (pulls live from Panel Data)
B23: Pair | D23: CORREL() Formula | F23: Live Result | G23: EViews Value
B24: CS vs Firm Size | D24: =CORREL(' Panel Data'!D3:D50,' Panel Data'!E3:E50) -> -0.65690774 | F24: =CORREL(' Panel Data'!D3:D50,' Panel Data'!E3:E50) -> -0.65690774 | G24: -0.6569
B25: CS vs Tangibility | D25: =CORREL(' Panel Data'!D3:D50,' Panel Data'!F3:F50) -> -0.36462583 | F25: =CORREL(' Panel Data'!D3:D50,' Panel Data'!F3:F50) -> -0.36462583 | G25: -0.3646
B26: CS vs ROA | D26: =CORREL(' Panel Data'!D3:D50,' Panel Data'!I3:I50) -> -0.75044306 | F26: =CORREL(' Panel Data'!D3:D50,' Panel Data'!I3:I50) -> -0.75044306 | G26: -0.7504
B27: CS vs ICR Log | D27: =CORREL(' Panel Data'!D3:D50,' Panel Data'!K3:K50) -> 0.24568953 | F27: =CORREL(' Panel Data'!D3:D50,' Panel Data'!K3:K50) -> 0.24568953 | G27: -0.708
B28: CS vs Rev Growth | D28: =CORREL(' Panel Data'!D3:D50,' Panel Data'!H3:H50) -> -0.019555345 | F28: =CORREL(' Panel Data'!D3:D50,' Panel Data'!H3:H50) -> -0.019555345 | G28: -0.0196
B29: CS vs NDTS | D29: =CORREL(' Panel Data'!D3:D50,' Panel Data'!J3:J50) -> -0.29365412 | F29: =CORREL(' Panel Data'!D3:D50,' Panel Data'!J3:J50) -> -0.29365412 | G29: -0.2937
B30: Tangibility vs NDTS | D30: =CORREL(' Panel Data'!F3:F50,' Panel Data'!J3:J50) -> 0.88251159 | F30: =CORREL(' Panel Data'!F3:F50,' Panel Data'!J3:J50) -> 0.88251159 | G30: 0.8825
B31: ROA vs ICR Log | D31: =CORREL(' Panel Data'!I3:I50,' Panel Data'!K3:K50) -> -0.23306284 | F31: =CORREL(' Panel Data'!I3:I50,' Panel Data'!K3:K50) -> -0.23306284 | G31: 0.8378

Sheet Regression Results
B1: PANEL REGRESSION RESULTS — Determinants of Capital Structure
B3: Dependent Variable | C3: Capital Structure (D/E Ratio)
B4: Method | C4: Panel Least Squares (Cross-Section Fixed Effects)
B5: Sample Period | C5: FY2018 – FY2025
B6: Companies (Cross-sections) | C6: 6
B7: Total Observations | C7: 48 (Balanced Panel)
B10: Variable | C10: Coefficient | D10: Std. Error | E10: t-Statistic | F10: Prob. | G10: Significance & Interpretation
B11: Constant (C) | C11: 7.520538 | D11: 1.403461 | E11: 5.358567 | F11: 0 | G11: p<0.01 — Strong positive intercept
B12: Firm Size (Log Assets) | C12: -0.65081 | D12: 0.138606 | E12: -4.695409 | F12: 0 | G12: p<0.01 — Larger firms USE LESS debt (Trade-off Theory)
B13: Non-Debt Tax Shield (NDTS) | C13: -49.77597 | D13: 12.86329 | E13: -3.869615 | F13: 0.0004 | G13: p<0.01 — Depreciation shield substitutes debt
B14: Return on Assets (ROA) | C14: -3.573802 | D14: 2.043847 | E14: -1.748566 | F14: 0.0889 | G14: p<0.10 — Profitable firms prefer internal funds (Pecking Order)
B15: Tangibility (FA/TA) | C15: -0.91313 | D15: 0.651352 | E15: -1.4019 | F15: 0.1695 | G15: Not significant at 10% level
B16: ICR Log | C16: -0.088213 | D16: 0.071915 | E16: -1.226624 | F16: 0.2279 | G16: Not significant — Debt service capacity not primary driver
B17: Revenue Growth | C17: -0.044461 | D17: 0.150338 | E17: -0.295741 | F17: 0.7691 | G17: Not significant — Growth rate doesn't affect leverage
B20: MODEL FIT & DIAGNOSTIC STATISTICS
B21: Metric | C21: value | E21: Metric | F21: Value
B22: R-Squared | C22: 0.821672 | E22: Adjusted R-Squared | F22: 0.767183
B23: S.E. of Regression | C23: 0.140944 | E23: F-Statistic | F23: 15.07954
B24: Sum Sq. Resid. | C24: 0.715148 | E24: Prob(F-statistic) | F24: 0
B25: Log Likelihood | C25: 32.84614 | E25: Durbin-Watson Stat | F25: 1.235245
B26: Akaike Info Criterion | C26: -0.868589 | E26: Schwarz Criterion | F26: -0.400789
B29: INTERPRETATION & THEORY ALIGNMENT
B30: Theory | D30: Evidence | F30: Explanation
B31: Trade-Off Theory | D31: Confirmed | F31: Firm Size (−0.65) — Larger firms with lower bankruptcy risk use less debt
B32: Pecking Order Theory | D32: Supported | F32: ROA (−3.57) — Profitable firms prefer retained earnings over debt
B33: Agency Cost Theory | D33: Partial | F33: NDTS (−49.78) — Depreciation tax shield reduces incentive for debt tax shield
B34: Market Timing Theory | D34: Not Supported | F34: Revenue Growth (−0.04, p=0.77) — No significant timing effect

Sheet comparison
B1: Polycab India & Industry Comparison
B3: Data: D/E Ratio — All Companies (FY2018–FY2025) | L3: Data: ROA (%) — All Companies
B4: Company | C4: 2018 | D4: 2019 | E4: 2020 | F4: 2021 | G4: 2022 | H4: 2023 | I4: 2024 | J4: 2025 | L4: Company | M4: 2018 | N4: 2019 | O4: 2020 | P4: 2021 | Q4: 2022 | R4: 2023 | S4: 2024 | T4: 2025
B5: Polycab India | C5: =' Panel Data'!D3 -> 0.1359 | D5: =' Panel Data'!D4 -> 0.0513 | E5: =' Panel Data'!D5 -> 0.0206 | F5: =' Panel Data'!D6 -> 0.0119 | G5: =' Panel Data'!D7 -> 0.0094 | H5: =' Panel Data'!D8 -> 0.0074 | I5: =' Panel Data'!D9 -> 0.0039 | J5: =' Panel Data'!D10 -> 0.0031 | L5: Polycab India | M5: =' Panel Data'!I3 -> 0.0859 | N5: =' Panel Data'!I4 -> 0.0897 | O5: =' Panel Data'!I5 -> 0.1169 | P5: =' Panel Data'!I6 -> 0.1143 | Q5: =' Panel Data'!I7 -> 0.1208 | R5: =' Panel Data'!I8 -> 0.1214 | S5: =' Panel Data'!I9 -> 0.1339 | T5: =' Panel Data'!I10 -> 0.1257
B6: KEI Industries | C6: =' Panel Data'!D11 -> 1.3917 | D6: =' Panel Data'!D12 -> 0.7699 | E6: =' Panel Data'!D13 -> 0.2435 | F6: =' Panel Data'!D14 -> 0.1877 | G6: =' Panel Data'!D15 -> 0.1662 | H6: =' Panel Data'!D16 -> 0.0626 | I6: =' Panel Data'!D17 -> 0.0527 | J6: =' Panel Data'!D18 -> 0.0375 | L6: KEI Industries | M6: =' Panel Data'!I11 -> 0.0653 | N6: =' Panel Data'!I12 -> 0.0655 | O6: =' Panel Data'!I13 -> 0.0783 | P6: =' Panel Data'!I14 -> 0.0898 | Q6: =' Panel Data'!I15 -> 0.1066 | R6: =' Panel Data'!I16 -> 0.1265 | S6: =' Panel Data'!I17 -> 0.1248 | T6: =' Panel Data'!I18 -> 0.0962
B7: Finolex Cables | C7: =' Panel Data'!D19 -> 0.0003 | D7: =' Panel Data'!D20 -> 0.0002 | E7: =' Panel Data'!D21 -> 0.0002 | F7: =' Panel Data'!D22 -> 0.0001 | G7: =' Panel Data'!D23 -> 0.0001 | H7: =' Panel Data'!D24 -> 0.0001 | I7: =' Panel Data'!D25 -> 0.0003 | J7: =' Panel Data'!D26 -> 0.0003 | L7: Finolex Cables | M7: =' Panel Data'!I19 -> 0.133 | N7: =' Panel Data'!I20 -> 0.1467 | O7: =' Panel Data'!I21 -> 0.13 | P7: =' Panel Data'!I22 -> 0.1418 | Q7: =' Panel Data'!I23 -> 0.1663 | R7: =' Panel Data'!I24 -> 0.125 | S7: =' Panel Data'!I25 -> 0.1415 | T7: =' Panel Data'!I26 -> 0.1396
B8: RR Kabel | C8: =' Panel Data'!D27 -> 0.7945 | D8: =' Panel Data'!D28 -> 0.3451 | E8: =' Panel Data'!D29 -> 0.4425 | F8: =' Panel Data'!D30 -> 0.4842 | G8: =' Panel Data'!D31 -> 0.4264 | H8: =' Panel Data'!D32 -> 0.4085 | I8: =' Panel Data'!D33 -> 0.1969 | J8: =' Panel Data'!D34 -> 0.1347 | L8: RR Kabel | M8: =' Panel Data'!I27 -> 0.066 | N8: =' Panel Data'!I28 -> 0.0925 | O8: =' Panel Data'!I29 -> 0.079 | P8: =' Panel Data'!I30 -> 0.0787 | Q8: =' Panel Data'!I31 -> 0.1043 | R8: =' Panel Data'!I32 -> 0.0721 | S8: =' Panel Data'!I33 -> 0.1039 | T8: =' Panel Data'!I34 -> 0.0887
B9: Havells India | C9: =' Panel Data'!D35 -> 0 | D9: =' Panel Data'!D36 -> 0.0144 | E9: =' Panel Data'!D37 -> 0 | F9: =' Panel Data'!D38 -> 0.1231 | G9: =' Panel Data'!D39 -> 0.0847 | H9: =' Panel Data'!D40 -> 0 | I9: =' Panel Data'!D41 -> 0 | J9: =' Panel Data'!D42 -> 0 | L9: Havells India | M9: =' Panel Data'!I35 -> 0.1562 | N9: =' Panel Data'!I36 -> 0.1662 | O9: =' Panel Data'!I37 -> 0.1221 | P9: =' Panel Data'!I38 -> 0.1245 | Q9: =' Panel Data'!I39 -> 0.1462 | R9: =' Panel Data'!I40 -> 0.1565 | S9: =' Panel Data'!I41 -> 0.161 | T9: =' Panel Data'!I42 -> 0.1588
B10: Universal Cables | C10: =' Panel Data'!D43 -> 0.4719 | D10: =' Panel Data'!D44 -> 0.5415 | E10: =' Panel Data'!D45 -> 0.6273 | F10: =' Panel Data'!D46 -> 0.5361 | G10: =' Panel Data'!D47 -> 0.5359 | H10: =' Panel Data'!D48 -> 0.4389 | I10: =' Panel Data'!D49 -> 0.4344 | J10: =' Panel Data'!D50 -> 0.4791 | L10: Universal Cables | M10: =' Panel Data'!I43 -> 0.0544 | N10: =' Panel Data'!I44 -> 0.0735 | O10: =' Panel Data'!I45 -> 0.0412 | P10: =' Panel Data'!I46 -> 0.0285 | Q10: =' Panel Data'!I47 -> 0.0272 | R10: =' Panel Data'!I48 -> 0.042 | S10: =' Panel Data'!I49 -> 0.0325 | T10: =' Panel Data'!I50 -> 0.026
B32: Data: ICR — All Companies (FY2018–FY2025) | L32: Data: Revenue Growth — Polycab India
B33: Company | C33: 2018 | D33: 2019 | E33: 2020 | F33: 2021 | G33: 2022 | H33: 2023 | I33: 2024 | J33: 2025 | L33: Year | M33: 2018 | N33: 2019 | O33: 2020 | P33: 2021 | Q33: 2022 | R33: 2023 | S33: 2024 | T33: 2025
B34: Polycab India | C34: =' Panel Data'!G3 -> 8.14 | D34: =' Panel Data'!G4 -> 8.58 | E34: =' Panel Data'!G5 -> 23.13 | F34: =' Panel Data'!G6 -> 26.38 | G34: =' Panel Data'!G7 -> 38.79 | H34: =' Panel Data'!G8 -> 32.06 | I34: =' Panel Data'!G9 -> 25.12 | J34: =' Panel Data'!G10 -> 18.65 | L34: Revenue Growth | M34: =' Panel Data'!H3 -> 0.1402 | N34: =' Panel Data'!H4 -> 0.1227 | O34: =' Panel Data'!H5 -> 0.0928 | P34: =' Panel Data'!H6 -> -0.0093 | Q34: =' Panel Data'!H7 -> 0.3871 | R34: =' Panel Data'!H8 -> 0.1511 | S34: =' Panel Data'!H9 -> 0.3092 | T34: =' Panel Data'!H10 -> 0.2052
B35: KEI Industries | C35: =' Panel Data'!G11 -> 2.82 | D35: =' Panel Data'!G12 -> 3.04 | E35: =' Panel Data'!G13 -> 3.54 | F35: =' Panel Data'!G14 -> 7.33 | G35: =' Panel Data'!G15 -> 13.7 | H35: =' Panel Data'!G16 -> 19.34 | I35: =' Panel Data'!G17 -> 18.75 | J35: =' Panel Data'!G18 -> 17.73 | L35: D/E Ratio | M35: =' Panel Data'!D3 -> 0.1359 | N35: =' Panel Data'!D4 -> 0.0513 | O35: =' Panel Data'!D5 -> 0.0206 | P35: =' Panel Data'!D6 -> 0.0119 | Q35: =' Panel Data'!D7 -> 0.0094 | R35: =' Panel Data'!D8 -> 0.0074 | S35: =' Panel Data'!D9 -> 0.0039 | T35: =' Panel Data'!D10 -> 0.0031
B36: Finolex Cables | C36: =' Panel Data'!G19 -> 550 | D36: =' Panel Data'!G20 -> 611 | E36: =' Panel Data'!G21 -> 257 | F36: =' Panel Data'!G22 -> 632 | G36: =' Panel Data'!G23 -> 394.5 | H36: =' Panel Data'!G24 -> 650 | I36: =' Panel Data'!G25 -> 433 | J36: =' Panel Data'!G26 -> 462
B37: RR Kabel | C37: =' Panel Data'!G27 -> 2.92 | D37: =' Panel Data'!G28 -> 6.28 | E37: =' Panel Data'!G29 -> 5.27 | F37: =' Panel Data'!G30 -> 7.24 | G37: =' Panel Data'!G31 -> 12.83 | H37: =' Panel Data'!G32 -> 6.95 | I37: =' Panel Data'!G33 -> 8.52 | J37: =' Panel Data'!G34 -> 7.82
B38: Havells India | C38: =' Panel Data'!G35 -> 44.36 | D38: =' Panel Data'!G36 -> 72.72 | E38: =' Panel Data'!G37 -> 47.73 | F38: =' Panel Data'!G38 -> 21.73 | G38: =' Panel Data'!G39 -> 32.26 | H38: =' Panel Data'!G40 -> 80.07 | I38: =' Panel Data'!G41 -> 65.95 | J38: =' Panel Data'!G42 -> 68.89
B39: Universal Cables | C39: =' Panel Data'!G43 -> 2.58 | D39: =' Panel Data'!G44 -> 3.74 | E39: =' Panel Data'!G45 -> 2.91 | F39: =' Panel Data'!G46 -> 2.43 | G39: =' Panel Data'!G47 -> 2.27 | H39: =' Panel Data'!G48 -> 2.57 | I39: =' Panel Data'!G49 -> 2.58 | J39: =' Panel Data'!G50 -> 2.12
B60: Data: EBIT & EPS — Polycab India
B61: Metric | C61: 2018 | D61: 2019 | E61: 2020 | F61: 2021 | G61: 2022 | H61: 2023 | I61: 2024 | J61: 2025
B62: EBIT (INR Cr) | C62: =' Polycab Cap Structure'!C29 -> 421 | D62: =' Polycab Cap Structure'!D29 -> 502 | E62: =' Polycab Cap Structure'!E29 -> 633 | F62: =' Polycab Cap Structure'!F29 -> 721 | G62: =' Polycab Cap Structure'!G29 -> 1089 | H62: =' Polycab Cap Structure'!H29 -> 1256 | I62: =' Polycab Cap Structure'!I29 -> 1598 | J62: =' Polycab Cap Structure'!J29 -> 1852
B63: EPS (INR) | C63: =' Polycab Cap Structure'!C35 -> 18.494488 | D63: =' Polycab Cap Structure'!D35 -> 22.203409 | E63: =' Polycab Cap Structure'!E35 -> 30.373061 | F63: =' Polycab Cap Structure'!F35 -> 34.78367 | G63: =' Polycab Cap Structure'!G35 -> 53.177917 | H63: =' Polycab Cap Structure'!H35 -> 60.996725 | I63: =' Polycab Cap Structure'!I35 -> 76.884943 | J63: =' Polycab Cap Structure'!J35 -> 87.861346
